README.rst
setup.py
klue_unit/__init__.py
klue_unit/testcase.py
klue_unit.egg-info/PKG-INFO
klue_unit.egg-info/SOURCES.txt
klue_unit.egg-info/dependency_links.txt
klue_unit.egg-info/not-zip-safe
klue_unit.egg-info/requires.txt
klue_unit.egg-info/top_level.txt
test/test_klue_unit.py
test/test_pep8.py