Metadata-Version: 1.1
Name: klue-unit
Version: 1.0.9
Summary: Library for unittesting json REST apis built with klue-client-server
Home-page: https://github.com/erwan-lemonnier/klue-unit
Author: Erwan Lemonnier
Author-email: erwan@lemonnier.se
License: BSD
Platform: any
Classifier: Environment :: Web Environment
Classifier: Intended Audience :: Developers
Classifier: License :: OSI Approved :: BSD License
Classifier: Operating System :: OS Independent
Classifier: Programming Language :: Python
Classifier: Topic :: Software Development :: Libraries :: Python Modules
